speedai/__init__.py
speedai/client.py
speedai/exceptions.py
speedai/models.py
speedai/py.typed
speedai-1.0.0.dist-info/licenses/LICENSE
speedai-1.0.0.dist-info/METADATA
speedai-1.0.0.dist-info/WHEEL
speedai-1.0.0.dist-info/top_level.txt
speedai-1.0.0.dist-info/RECORD
