Metadata-Version: 2.4
Name: speedai
Version: 1.0.0
Summary: Python package for SpeedAI document and text processing API
Home-page: https://github.com/SpeedAI-team/speedai-py
Author: SpeedAI
Author-email: SpeedAI <team@speedai.chat>
License: MIT
Project-URL: Homepage, https://github.com/SpeedAI-team/speedai-py
Project-URL: Documentation, https://github.com/SpeedAI-team/speedai-py/wiki
Project-URL: Repository, https://github.com/SpeedAI-team/speedai-py
Project-URL: Bug Tracker, https://github.com/SpeedAI-team/speedai-py/issues
Classifier: Development Status :: 5 - Production/Stable
Classifier: Intended Audience :: Developers
Classifier: License :: OSI Approved :: MIT License
Classifier: Programming Language :: Python :: 3
Classifier: Programming Language :: Python :: 3.6
Classifier: Programming Language :: Python :: 3.7
Classifier: Programming Language :: Python :: 3.8
Classifier: Programming Language :: Python :: 3.9
Classifier: Programming Language :: Python :: 3.10
Classifier: Programming Language :: Python :: 3.11
Classifier: Operating System :: OS Independent
Classifier: Topic :: Software Development :: Libraries :: Python Modules
Requires-Python: >=3.6
License-File: LICENSE
Requires-Dist: requests>=2.25.0
Requires-Dist: aiohttp>=3.8.0
Requires-Dist: typing-extensions>=4.0.0
Provides-Extra: dev
Requires-Dist: pytest>=7.0.0; extra == "dev"
Requires-Dist: pytest-asyncio>=0.20.0; extra == "dev"
Requires-Dist: black>=22.0.0; extra == "dev"
Requires-Dist: flake8>=5.0.0; extra == "dev"
Requires-Dist: twine>=4.0.0; extra == "dev"
Requires-Dist: build>=0.10.0; extra == "dev"
Dynamic: author
Dynamic: home-page
Dynamic: license-file
Dynamic: requires-python
